forcealign/__init__.py
forcealign/forcealign.py
forcealign/transcriber.py
forcealign/utils.py
forcealign-1.1.9.dist-info/LICENSE
forcealign-1.1.9.dist-info/METADATA
forcealign-1.1.9.dist-info/WHEEL
forcealign-1.1.9.dist-info/top_level.txt
forcealign-1.1.9.dist-info/RECORD
