Metadata-Version: 2.1
Name: forcealign
Version: 1.1.9
Summary: A Python library for forced alignment of English text to English audio.
Home-page: https://github.com/lukerbs/forcealign
Author: Luke Kerbs
Keywords: force align,forced alignment,audio segmentation,audio forced alignment,python forced alignment,phoneme,generate subtitles
Classifier: Programming Language :: Python :: 3
Classifier: License :: OSI Approved :: MIT License
Classifier: Operating System :: OS Independent
License-File: LICENSE
Requires-Dist: torch >=2.2.1
Requires-Dist: torchaudio >=2.2.1
Requires-Dist: pydub >=0.25.1
Requires-Dist: g2p-en >=2.1.0
Requires-Dist: sox
Requires-Dist: soundfile
Requires-Dist: ffmpeg-python
